rawxio/__init__.py
rawxio/data_model.py
rawxio/rawx.py
rawxio/utils.py
rawxio-0.2.0.dist-info/LICENSE
rawxio-0.2.0.dist-info/WHEEL
rawxio-0.2.0.dist-info/METADATA
rawxio-0.2.0.dist-info/RECORD
